snaketools/__init__.py
snaketools/errors.py
snaketools/snaketools.py
snaketools-0.0.8.dist-info/METADATA
snaketools-0.0.8.dist-info/RECORD
snaketools-0.0.8.dist-info/WHEEL
snaketools-0.0.8.dist-info/top_level.txt
