Metadata-Version: 2.1
Name: snaketools
Version: 0.0.8
Summary: Small library of helper tools for setting up, graphing, and working with Snakemake rules.
Home-page: https://github.com/xguse/snaketools
Author: Gus Dunn
Author-email: w.gus.dunn@gmail.com
License: MIT license
Keywords: snaketools
Platform: UNKNOWN
Classifier: Development Status :: 2 - Pre-Alpha
Classifier: Intended Audience :: Developers
Classifier: License :: OSI Approved :: MIT License
Classifier: Natural Language :: English
Classifier: Programming Language :: Python :: 2
Classifier: Programming Language :: Python :: 2.6
Classifier: Programming Language :: Python :: 2.7
Classifier: Programming Language :: Python :: 3
Classifier: Programming Language :: Python :: 3.3
Classifier: Programming Language :: Python :: 3.4
Classifier: Programming Language :: Python :: 3.5
Classifier: Programming Language :: Python :: 3.6
Requires-Dist: snakemake (>=4.3.1)
Requires-Dist: munch (>=2.2.0)
Requires-Dist: logzero (>=1.3.0)
